{
    "tier1": [
        {
            "name": "Ant",
            "attack": 2,
            "hp": 1,
            "ability1": "Faint: Give a random friend +2/+1",
            "ability2": "Faint: Give a random friend +4/+2",
            "ability3": "Faint: Give a random friend +6/+3",
            "path": "./assets/img/ant.png"
        },
        {
            "name": "Beaver",
            "attack": 2,
            "hp": 2,
            "ability1": "Sell: Give 2 random friends +1 Health",
            "ability2": "Sell: Give 2 random friends +2 Health",
            "ability3": "Sell: Give 2 random friends +3 Health",
            "path": "./assets/img/beaver.png"
        },
        {
            "name": "Beetle",
            "attack": 2,
            "hp": 3,
            "ability1": "Eat shop food: Give shop animals +1 Health",
            "ability2": "Eat shop food: Give shop animals +2 Health",
            "ability3": "Eat shop food: Give shop animals +3 Health",
            "path": "./assets/img/beetle.png"
        },
        {
            "name": "Bluebird",
            "attack": 2,
            "hp": 1,
            "ability1": "End turn: Give left-most friend +1 Attack",
            "ability2": "End turn: Give left-most friend +2 Attack",
            "ability3": "End turn: Give left-most friend +3 Attack",
            "path": "./assets/img/bluebird.png"
        },
        {
            "name": "Cricket",
            "attack": 1,
            "hp": 2,
            "ability1": "Faint: Summon a 1/1 Cricket",
            "ability2": "Faint: Summon a 3/3 Cricket",
            "ability3": "Faint: Summon a 3/3 Cricket",
            "path": "./assets/img/cricket.png"
        },
        {
            "name": "Fish",
            "attack": 2,
            "hp": 3,
            "ability1": "Level-up: Give all friends +1/+1",
            "ability2": "Level-up: Give all friends +2/+2",
            "ability3": "Animal is already at max level",
            "path": "./assets/img/fish.png"
        },
        {
            "name": "Ladybug",
            "attack": 1,
            "hp": 3,
            "ability1": "Buy food: Gain +1/+1 until end of battle",
            "ability2": "Buy food: Gain +2/+2 until end of battle",
            "ability3": "Buy food: Gain +3/+3 until end of battle",
            "path": "./assets/img/ladybug.png"
        },
        {
            "name": "Mosquito",
            "attack": 2,
            "hp": 2,
            "ability1": "Start of battle: Deal 1 damage to a random enemy",
            "ability2": "Start of battle: Deal 2 damage to a random enemy",
            "ability3": "Start of battle: Deal 3 damage to a random enemy",
            "path": "./assets/img/mosquito.png"
        },
        {
            "name": "Pig",
            "attack": 2,
            "hp": 2,
            "ability1": "Sell: Gain an extra 1 gold",
            "ability2": "Sell: Gain an extra 2 gold",
            "ability3": "Sell: Gain an extra 3 gold",
            "path": "./assets/img/pig.png"
        }
    ],
    "tier2": [
        {
            "name": "Bat",
            "attack": 1,
            "hp": 3,
            "ability1": "Start of battle: Make 1 enemy Weak",
            "ability2": "Start of battle: Make 2 enemies Weak",
            "ability3": "Start of battle: Make 2 enemies Weak",
            "path": "./assets/img/bat.png"
        },
        {
            "name": "Dog",
            "attack": 2,
            "hp": 2,
            "ability1": "Friend summoned: Gain +1 Attack or +1 Health",
            "ability2": "Friend summoned: Gain +2 Attack or +2 Health",
            "ability3": "Friend summoned: Gain +3 Attack or +3 Health",
            "path": "./assets/img/dog.png"
        },
        {
            "name": "Dromedary",
            "attack": 2,
            "hp": 4,
            "ability1": "Start of turn: Give shop animals +1/+1",
            "ability2": "Start of turn: Give shop animals +2/+2",
            "ability3": "Start of turn: Give shop animals +3/+3",
            "path": "./assets/img/dromedary.png"
        },
        {
            "name": "Flamingo",
            "attack": 3,
            "hp": 1,
            "ability1": "Faint: Give the two friends behind +1/+1",
            "ability2": "Faint: Give the two friends behind +2/+2",
            "ability3": "Faint: Give the two friends behind +3/+3",
            "path": "./assets/img/flamingo.png"
        },
        {
            "name": "Hedgehog",
            "attack": 3,
            "hp": 2,
            "ability1": "Faint: Deal 2 damage to all",
            "ability2": "Faint: Deal 4 damage to all",
            "ability3": "Faint: Deal 6 damage to all",
            "path": "./assets/img/hedgehog.png"
        },
        {
            "name": "Peacock",
            "attack": 1,
            "hp": 5,
            "ability1": "Hurt: Gain +2 Attack",
            "ability2": "Hurt: Gain +4 Attack",
            "ability3": "Hurt: Gain +6 Attack",
            "path": "./assets/img/peacock.png"
        },
        {
            "name": "Rat",
            "attack": 4,
            "hp": 5,
            "ability1": "Faint: Summon one 1/1 Dirty Rat for the opponent that betrays him (1 Damage to front animal on attack)",
            "ability2": "Faint: Summon one 1/1 Dirty Rat for the opponent that betrays him (1 Damage to front animal on attack)",
            "ability3": "Faint: Summon one 1/1 Dirty Rat for the opponent that betrays him (1 Damage to front animal on attack)",
            "path": "./assets/img/rat.png"
        },
        {
            "name": "Shrimp",
            "attack": 2,
            "hp": 1,
            "ability1": "Friend solt: Give a random friend +1 Health",
            "ability2": "Friend solt: Give a random friend +2 Health",
            "ability3": "Friend solt: Give a random friend +3 Health",
            "path": "./assets/img/shrimp.png"
        },
        {
            "name": "Spider",
            "attack": 2,
            "hp": 2,
            "ability1": "Faint: Summon one tier 3 animal as a 2/2",
            "ability2": "Faint: Summon one tier 3 animal as a 4/4",
            "ability3": "Faint: Summon one tier 3 animal as a 6/6",
            "path": "./assets/img/spider.png"
        },
        {
            "name": "Swan",
            "attack": 3,
            "hp": 4,
            "ability1": "Start of turn: Gain 1 gold",
            "ability2": "Start of turn: Gain 2 gold",
            "ability3": "Start of turn: Gain 3 gold",
            "path": "./assets/img/swan.png"
        },
        {
            "name": "Tabby Cat",
            "attack": 4,
            "hp": 3,
            "ability1": "Eats shop food: Give friends +1 Attack until end of battle",
            "ability2": "Eats shop food: Give friends +2 Attack until end of battle",
            "ability3": "Eats shop food: Give friends +3 Attack until end of battle",
            "path": "./assets/img/tabbycat.png"
        }
    ],
    "tier3": [
        {
            "name": "Blowfish",
            "attack": 3,
            "hp": 5,
            "ability1": "Hurt: Deal 2 damage to a random enemy",
            "ability2": "Hurt: Deal 4 damage to a random enemy",
            "ability3": "Hurt: Deal 6 damage to a random enemy",
            "path": "./assets/img/blowfish.png"
        },
        {
            "name": "Caterpillar",
            "attack": 1,
            "hp": 4,
            "ability1": "Start of turn: Gain 1 Experience",
            "ability2": "Start of turn: Gain 1 Experience",
            "ability3": "Start of battle: Evolve into a Butterfly (Copy stats of highest friend on field)",
            "path": "./assets/img/caterpillar.png"
        },
        {
            "name": "Hatching Chick",
            "attack": 1,
            "hp": 1,
            "ability1": "End turn: Give +5/+5 to friend ahead until end of battle",
            "ability2": "End turn: Give +2/+2 to friend ahead",
            "ability3": "Start of turn: Give +1 Experience to friend ahead",
            "path": "./assets/img/hatchingchick.png"
        },
        {
            "name": "Owl",
            "attack": 5,
            "hp": 3,
            "ability1": "Sell: Give a random friend +2/+2",
            "ability2": "Sell: Give a random friend +2/+2",
            "ability3": "Sell: Give a random friend +2/+2",
            "path": "./assets/img/owl.png"
        },
        {
            "name": "Puppy",
            "attack": 1,
            "hp": 1,
            "ability1": "End turn: If you have 2 or more gold, gain +2/+2",
            "ability2": "End turn: If you have 2 or more gold, gain +4/+4",
            "ability3": "End turn: If you have 2 or more gold, gain +6/+6",
            "path": "./assets/img/puppy.png"
        },
        {
            "name": "Rabbit",
            "attack": 3,
            "hp": 2,
            "ability1": "Friend eats shop food: Give it +1 Health",
            "ability2": "Friend eats shop food: Give it +2 Health",
            "ability3": "Friend eats shop food: Give it +3 Health",
            "path": "./assets/img/rabbit.png"
        },
        {
            "name": "Sheep",
            "attack": 2,
            "hp": 2,
            "ability1": "Faint: Summon two 2/2 Rams",
            "ability2": "Faint: Summon two 4/4 Rams",
            "ability3": "Faint: Summon two 6/6 Rams",
            "path": "./assets/img/sheep.png"
        },
        {
            "name": "Snail",
            "attack": 2,
            "hp": 2,
            "ability1": "Buy: If you lost last battle, give all friends +2/+1",
            "ability2": "Buy: If you lost last battle, give all friends +4/+2",
            "ability3": "Buy: If you lost last battle, give all friends +6/+3",
            "path": "./assets/img/snail.png"
        },
        {
            "name": "Tropical Fish",
            "attack": 2,
            "hp": 4,
            "ability1": "End turn: Give adjacent friends +1 Health",
            "ability2": "End turn: Give adjacent friends +2 Health",
            "ability3": "End turn: Give adjacent friends +3 Health",
            "path": "./assets/img/tropicalfish.png"
        },
        {
            "name": "Turtle",
            "attack": 2,
            "hp": 4,
            "ability1": "Give friend behind Melon Armor",
            "ability2": "Give 2 friends behind Melon Armor",
            "ability3": "Give 3 friends behind Melon Armor",
            "path": "./assets/img/turtle.png"
        }
    ],
    "tier4": [
        {
            "name": "Bison",
            "attack": 6,
            "hp": 6,
            "ability1": "End turn: Gain +2/+2 if there is at least one Lvl. 3 friend",
            "ability2": "End turn: Gain +4/+4 if there is at least one Lvl. 3 friend",
            "ability3": "End turn: Gain +6/+6 if there is at least one Lvl. 3 friend",
            "path": "./assets/img/bison.png"
        },
        {
            "name": "Buffalo",
            "attack": 5,
            "hp": 5,
            "ability1": "Friend bought: Gain +1/+1",
            "ability2": "Friend bought: Gain +2/+2",
            "ability3": "Friend bought: Gain +3/+3",
            "path": "./assets/img/buffalo.png"
        },
        {
            "name": "Deer",
            "attack": 1,
            "hp": 1,
            "ability1": "Faint: Summon a 5/5 Bus with Splash Attack",
            "ability2": "Faint: Summon a 10/10 Bus with Splash Attack",
            "ability3": "Faint: Summon a 15/15 Bus with Splash Attack",
            "path": "./assets/img/deer.png"
        },
        {
            "name": "Llama",
            "attack": 2,
            "hp": 5,
            "ability1": "End turn: If you habe 4 or less animals, gain +2/+2",
            "ability2": "End turn: If you habe 4 or less animals, gain +4/+4",
            "ability3": "End turn: If you habe 4 or less animals, gain +6/+6",
            "path": "./assets/img/llama.png"
        },
        {
            "name": "Lobster",
            "attack": 3,
            "hp": 3,
            "ability1": "Friend summoned: Give it +2/+2 when not in battle",
            "ability2": "Friend summoned: Give it +4/+4 when not in battle",
            "ability3": "Friend summoned: Give it +6/+6 when not in battle",
            "path": "./assets/img/lobster.png"
        },
        {
            "name": "Poodle",
            "attack": 4,
            "hp": 2,
            "ability1": "End turn: Give +1/+1 to different tier animals",
            "ability2": "End turn: Give +2/+2 to different tier animals",
            "ability3": "End turn: Give +3/+3 to different tier animals",
            "path": "./assets/img/poodle.png"
        },
        {
            "name": "Rooster",
            "attack": 3,
            "hp": 3,
            "ability1": "Faint: Summon a Chick with the same Attack as this",
            "ability2": "Faint: Summon 2 Chicks with the same Attack as this",
            "ability3": "Faint: Summon 3 Chicks with the same Attack as this",
            "path": "./assets/img/rooster.png"
        },
        {
            "name": "Skunk",
            "attack": 3,
            "hp": 5,
            "ability1": "Start of battle: Reduce the highest Health enemy by 33%",
            "ability2": "Start of battle: Reduce the highest Health enemy by 66%",
            "ability3": "Start of battle: Reduce the highest Health enemy by 100%",
            "path": "./assets/img/skunk.png"
        },
        {
            "name": "Squirrel",
            "attack": 2,
            "hp": 2,
            "ability1": "Buy: Clear and fill shops with food",
            "ability2": "Buy: Clear and fill shops with food",
            "ability3": "Buy: Clear and fill shops with food",
            "path": "./assets/img/squirrel.png"
        },
        {
            "name": "Worm",
            "attack": 1,
            "hp": 1,
            "ability1": "Eats shop food: Gain +1/+1",
            "ability2": "Eats shop food: Gain +2/+2",
            "ability3": "Eats shop food: Gain +3/+3",
            "path": "./assets/img/worm.png"
        }
    ],
    "tier5": [
        {
            "name": "Chicken",
            "attack": 3,
            "hp": 4,
            "ability1": "Buy tier 1 animal: Give current and future shop animals +1/+1",
            "ability2": "Buy tier 1 animal: Give current and future shop animals +2/+2",
            "ability3": "Buy tier 1 animal: Give current and future shop animals +3/+3",
            "path": "./assets/img/chicken.png"
        },
        {
            "name": "Cow",
            "attack": 4,
            "hp": 6,
            "ability1": "Buy: Replace food shop with 2 free milk that gives +2/+2",
            "ability2": "Buy: Replace food shop with 2 free milk that gives +2/+2",
            "ability3": "Buy: Replace food shop with 2 free milk that gives +2/+2",
            "path": "./assets/img/cow.png"
        },
        {
            "name": "Eagle",
            "attack": 6,
            "hp": 5,
            "ability1": "Faint: Summon one Lvl. 1 tier 6 animal",
            "ability2": "Faint: Summon one Lvl. 2 tier 6 animal",
            "ability3": "Faint: Summon one Lvl. 3 tier 6 animal",
            "path": "./assets/img/eagle.png"
        },
        {
            "name": "Goat",
            "attack": 4,
            "hp": 5,
            "ability1": "Friend bought: Gain 1 gold",
            "ability2": "Friend bought: Gain 1 gold",
            "ability3": "Friend bought: Gain 1 gold",
            "path": "./assets/img/goat.png"
        },
        {
            "name": "Microbe",
            "attack": 1,
            "hp": 1,
            "ability1": "Faint: Make all animals Weak",
            "ability2": "Faint: Make all animals Weak",
            "ability3": "Faint: Make all animals Weak",
            "path": "./assets/img/microbe.png"
        },
        {
            "name": "Rhino",
            "attack": 5,
            "hp": 6,
            "ability1": "Knock out: Deal 4 damage to the first enemy",
            "ability2": "Knock out: Deal 8 damage to the first enemy",
            "ability3": "Knock out: Deal 12 damage to the first enemy",
            "path": "./assets/img/rhino.png"
        },
        {
            "name": "Scorpion",
            "attack": 1,
            "hp": 1,
            "ability1": "No ability (comes with poison attack)",
            "ability2": "No ability (comes with poison attack)",
            "ability3": "No ability (comes with poison attack)",
            "path": "./assets/img/scorpion.png"
        },
        {
            "name": "Seal",
            "attack": 3,
            "hp": 6,
            "ability1": "Eats shop food: Give 2 random friends +1/+1",
            "ability2": "Eats shop food: Give 2 random friends +2/+2",
            "ability3": "Eats shop food: Give 2 random friends +3/+3",
            "path": "./assets/img/seal.png"
        }
    ],
    "tier6": [
        {
            "name": "Dragon",
            "attack": 6,
            "hp": 8,
            "ability1": "Buy tier 1 animal: Give all friends +1/+1",
            "ability2": "Buy tier 1 animal: Give all friends +2/+2",
            "ability3": "Buy tier 1 animal: Give all friends +3/+3",
            "path": "./assets/img/dragon.png"
        },
        {
            "name": "Gorilla",
            "attack": 6,
            "hp": 6,
            "ability1": "Hurt: Gain Coconut Shield (no damage once)",
            "ability2": "Hurt: Gain Coconut Shield (no damage once)",
            "ability3": "Hurt: Gain Coconut Shield (no damage once)",
            "path": "./assets/img/gorilla.png"
        },
        {
            "name": "Leopard",
            "attack": 6,
            "hp": 4,
            "ability1": "Start of battle: Deal 50% Attack damage to a random enemy",
            "ability2": "Start of battle: Deal 50% Attack damage to 2 random enemies",
            "ability3": "Start of battle: Deal 50% Attack damage to 3 random enemies",
            "path": "./assets/img/leopard.png"
        },
        {
            "name": "Mammoth",
            "attack": 2,
            "hp": 6,
            "ability1": "Faint: Give all friends +2/+2",
            "ability2": "Faint: Give all friends +4/+4",
            "ability3": "Faint: Give all friends +6/+6",
            "path": "./assets/img/mammoth.png"
        },
        {
            "name": "Octopus",
            "attack": 8,
            "hp": 8,
            "ability1": "Level-up: Gain +8/+8",
            "ability2": "Level-up: Gain +8/+8 and new ability",
            "ability3": "Deal 5 damage to all enemies",
            "path": "./assets/img/octopus.png"
        },
        {
            "name": "Sauropod",
            "attack": 4,
            "hp": 12,
            "ability1": "Buy food: Gain 1 gold",
            "ability2": "Buy food: Gain 1 gold",
            "ability3": "Buy food: Gain 1 gold",
            "path": "./assets/img/sauropod.png"
        },
        {
            "name": "Tyrannosaurus",
            "attack": 9,
            "hp": 4,
            "ability1": "End turn: If you have 3 or more gold, give other friends +2/+2",
            "ability2": "End turn: If you have 3 or more gold, give other friends +4/+4",
            "ability3": "End turn: If you have 3 or more gold, give other friends +6/+6",
            "path": "./assets/img/tyrannosaurus.png"
        }
    ]
}