{
    "tier1": [
        {
            "name": "Apple",
            "id": "apple",
            "ability": "Give an animal +1/+1",
            "path": "./assets/img/apple.png"
        },
        {
            "name": "Honey",
            "id": "honey",
            "ability": "Give an animal Faint: Summon 1/1 Honey Bee",
            "path": "./assets/img/honey.png",
            "special": {
                "name": "Bee",
                "attack": 1,
                "hp": 1,
                "path": "./assets/img/bee.png"
            }
        }
    ],
    "tier2": [
        {
            "name": "Cupcake",
            "id": "cupcake",
            "ability": "Give an animal +3/+3 until end of battle",
            "path": "./assets/img/cupcake.png"
        },
        {
            "name": "Meat Bone",
            "id": "meatbone meat bone",
            "ability": "Give an animal Bone Attack: 5 damage more on first attack",
            "path": "./assets/img/bonemeat.png"
        },
        {
            "name": "Sleeping Pill",
            "id": "sleepingpill sleeping pill",
            "ability": "Make friendly animal faint (this costs 1 Gold)",
            "path": "./assets/img/pill.png"
        }
    ],
    "tier3": [
        {
            "name": "Garlic",
            "id": "garlic",
            "ability": "Give an animal Garlic Armor",
            "path": "./assets/img/garlic.png",
            "special": {
                "name": "Garlic Armor",
                "ability": "Reduce damage taken by 2 everytime",
                "path": "./assets/img/garlic.png"
            }
        },
        {
            "name": "Salad Bowl",
            "id": "saladbowl salad bowl",
            "ability": "Give 2 random animals +1/+1",
            "path": "./assets/img/saladbowl.png"
        }
    ],
    "tier4": [
        {
            "name": "Canned Food",
            "id": "cannedfood canned food",
            "ability": "Give all current and future shop animals +2/+2",
            "path": "./assets/img/cannedfood.png"
        },
        {
            "name": "Pear",
            "id": "pear",
            "ability": "Give animal +2/+2",
            "path": "./assets/img/pear.png"
        }
    ],
    "tier5": [
        {
            "name": "Chili",
            "id": "chili",
            "ability": "Give an animal Splash Attack",
            "path": "./assets/img/chili.png",
            "special": {
                "name": "Splash Attack",
                "ability": "Deal up to 5 Damage to second enemy in line",
                "path": "./assets/img/chili.png"
            }
        },
        {
            "name": "Chocolate",
            "id": "chocolate",
            "ability": "Give animal +1 Experience",
            "path": "./assets/img/chocolate.png"
        },
        {
            "name": "Sushi",
            "id": "sushi",
            "ability": "Give 3 random animals +1/+1",
            "path": "./assets/img/sushi.png"
        }
    ],
    "tier6": [
        {
            "name": "Melon",
            "id": "melon",
            "ability": "Give an animal Melon Armor",
            "path": "./assets/img/melon.png",
            "special": {
                "name": "Melon Armor",
                "ability": "Prevent 20 damage on first attack",
                "path": "./assets/img/melon.png"
            }
        },
        {
            "name": "Mushroom",
            "id": "mushroom",
            "ability": "Give animal Extra Life as a 1/1",
            "path": "./assets/img/mushroom.png",
            "special": {
                "name": "Extra Life",
                "ability": "Faint: Resummon as 1/1",
                "path": "./assets/img/mushroom.png"
            }
        },
        {
            "name": "Pizza",
            "id": "pizza",
            "ability": "Give 2 random animals +2/+2",
            "path": "./assets/img/pizza.png"
        },
        {
            "name": "Steak",
            "id": "steak",
            "ability": "Give an animal 20 Steak Attack",
            "path": "./assets/img/steak.png",
            "special": {
                "name": "Steak Attack",
                "ability": "Deal 20 more Damage, once",
                "path": "./assets/img/steak.png"
            }
        }
    ]
}